sputil/__init__.py
sputil/base.py
sputil/splunk.py
sputil/stress.py
sputil-0.3.7.data/scripts/sputil
sputil-0.3.7.dist-info/METADATA
sputil-0.3.7.dist-info/RECORD
sputil-0.3.7.dist-info/WHEEL
sputil-0.3.7.dist-info/top_level.txt
