Metadata-Version: 2.1
Name: sputil
Version: 0.3.7
Summary: Splunk Utility
Home-page: https://github.com/GamjaPower/splunk-util
Author: Jason Shim
Author-email: sst9696@gmail.com
License: MIT
Platform: UNKNOWN
Classifier: Programming Language :: Python :: 2
Classifier: License :: OSI Approved :: MIT License
Classifier: Operating System :: OS Independent
Requires-Dist: requests (>=2.0.0)
Requires-Dist: splunk-sdk (>=1.6.0)
Requires-Dist: pyutil (>=3.0.0)
